budgetplanner/__init__.py
budgetplanner/budget_subpackage/__init__.py
budgetplanner/budget_subpackage/basicmembership.py
budgetplanner/budget_subpackage/freemembership.py
budgetplanner/budget_subpackage/premiummembership.py
budgetplanner/budget_subpackage/test_budget_subpackge.py
budgetplanner/user_subpackage/__init__.py
budgetplanner/user_subpackage/bank_info.py
budgetplanner/user_subpackage/personal_info.py
budgetplanner/user_subpackage/service.py
package/__init__.py
package/budget_subpackage/__init__.py
package/budget_subpackage/basicmembership.py
package/budget_subpackage/freemembership.py
package/budget_subpackage/premiummembership.py
package/budget_subpackage/test_budget_subpackge.py
package/user_subpackage/__init__.py
package/user_subpackage/bank_info.py
package/user_subpackage/personal_info.py
package/user_subpackage/service.py
budgetplanner-0.1.dist-info/LICENSE.txt
budgetplanner-0.1.dist-info/METADATA
budgetplanner-0.1.dist-info/WHEEL
budgetplanner-0.1.dist-info/top_level.txt
budgetplanner-0.1.dist-info/RECORD
