Metadata-Version: 2.1
Name: budgetplanner
Version: 0.1
Summary: When piggy bank becomes your financial assisstant
Home-page: https://github.com/Saisree-123/DATA533-LAB4
Author: Saisree GR
Author-email: saisree.gr@gmail.com
License: MIT
Platform: UNKNOWN
License-File: LICENSE.txt
